Metadata-Version: 2.1
Name: tag-formatter
Version: 1.1.1
Summary: Tag-formatter is a Python Package designed to format strings that based on user-input.
Home-page: https://github.com/jay3332/tag-formatter
Author: jay3332
License: UNKNOWN
Platform: UNKNOWN
Classifier: Programming Language :: Python :: 3
Classifier: License :: OSI Approved :: MIT License
Classifier: Operating System :: OS Independent
